pyrsess-0.1.1.dist-info/METADATA
pyrsess-0.1.1.dist-info/WHEEL
pyrsess-0.1.1.dist-info/license_files/LICENSE.txt
pyrsess/__init__.py
pyrsess/__init__.pyi
pyrsess/py.typed
pyrsess/pyrsess.cpython-39-x86_64-linux-gnu.so
pyrsess-0.1.1.dist-info/RECORD
