Metadata-Version: 2.1
Name: pyrsess
Version: 0.1.1
Classifier: Programming Language :: Rust
Classifier: Programming Language :: Python :: Implementation :: CPython
Classifier: Programming Language :: Python :: Implementation :: PyPy
License-File: LICENSE.txt
Summary: Implementation of the enumerative sphere shaping algorithm for probabilistic constellation shaping.
Keywords: communications,probabilistic,shaping,ess,oess
Author: Frederik Ritter <uoogk@student.kit.edu>, Andrej Rode <rode@kit.edu>, Laurent Schmalen <laurent.schmalen@kit.edu>
Author-email: Frederik Ritter <uoogk@student.kit.edu>, Andrej Rode <rode@kit.edu>, Laurent Schmalen <laurent.schmalen@kit.edu>
License: GPL-3.0
Requires-Python: >=3.7
Project-URL: Source Code, https://github.com/kit-cel/rsess
